MANIFEST.in
README.rst
setup.cfg
setup.py
cognito/__init__.py
cognito.egg-info/PKG-INFO
cognito.egg-info/SOURCES.txt
cognito.egg-info/dependency_links.txt
cognito.egg-info/entry_points.txt
cognito.egg-info/not-zip-safe
cognito.egg-info/requires.txt
cognito.egg-info/top_level.txt
cognito/check/__init__.py
cognito/modules/__init__.py
cognito/process/__init__.py
cognito/report/__init__.py
cognito/scripts/__init__.py
cognito/scripts/cli.py
cognito/scripts/templates/bar.html
cognito/scripts/templates/base.html
cognito/scripts/templates/index.html
cognito/story/__init__.py
cognito/table/__init__.py
cognito/transform/__init__.py