Metadata-Version: 2.1
Name: cognito
Version: 0.0.1b2.dev0
Summary: Auto ML Dataset Transformer & Auto Data Storyteller
Home-page: https://github.com/cleverinsight
Author: Bastin Robins .J
Author-email: robin@cleverinsight.co
License: BSD
Download-URL: https://github.com/CleverInsight/cognito/releases
Project-URL: Bug Tracker, https://github.com/Cleverinsight/congito/issues
Project-URL: Documentation, https://cognito.readthedocs.io/en/latest/
Project-URL: Source Code, https://github.com/Cleverinsight/congito
Keywords: Automated Data Storyteller,Data Wrangler,Data Preprocessing,Machine Learning,Hot Encoder,Outlier Detection
Platform: UNKNOWN
Classifier: Development Status :: 4 - Beta
Classifier: Environment :: Console
Classifier: Intended Audience :: Developers
Classifier: Operating System :: OS Independent
Classifier: License :: OSI Approved :: MIT License
Classifier: Programming Language :: Python :: 2
Classifier: Programming Language :: Python :: 2.7
Classifier: Programming Language :: Python :: 3
Classifier: Programming Language :: Python :: 3.5
Classifier: Programming Language :: Python :: 3.6
Classifier: Programming Language :: Python :: 3.7
Classifier: Programming Language :: Python :: 3.8
Classifier: Programming Language :: Python
Classifier: Topic :: Internet :: WWW/HTTP
Classifier: Topic :: Software Development :: Libraries :: Python Modules
Classifier: Topic :: Utilities
Classifier: Topic :: Scientific/Engineering
Provides-Extra: test
